pypaint/__init__.py
pypaint/api.py
pypaint-0.1.4.3.dist-info/LICENSE
pypaint-0.1.4.3.dist-info/METADATA
pypaint-0.1.4.3.dist-info/WHEEL
pypaint-0.1.4.3.dist-info/top_level.txt
pypaint-0.1.4.3.dist-info/RECORD
