Metadata-Version: 2.1
Name: pypaint
Version: 0.1.4.3
Summary: Drawing module for python
Home-page: https://github.com/ErikBavenstrand/pypaint
Author: Erik Bavenstrand
Author-email: erik.bavenstrands@gmail.com
License: UNKNOWN
Platform: UNKNOWN
Classifier: Programming Language :: Python :: 3
Classifier: License :: OSI Approved :: MIT License
Classifier: Operating System :: OS Independent
